{"namespace":"ScolloPaintingDesignSystem_9ecefb","components":[{"name":"Badge","sourcePath":"components/core/Badge.jsx"},{"name":"BeforeAfter","sourcePath":"components/core/BeforeAfter.jsx"},{"name":"Button","sourcePath":"components/core/Button.jsx"},{"name":"Card","sourcePath":"components/core/Card.jsx"},{"name":"Input","sourcePath":"components/core/Input.jsx"},{"name":"PhoneLink","sourcePath":"components/core/PhoneLink.jsx"},{"name":"SectionHeading","sourcePath":"components/core/SectionHeading.jsx"},{"name":"Select","sourcePath":"components/core/Select.jsx"},{"name":"ServiceCard","sourcePath":"components/core/ServiceCard.jsx"},{"name":"Textarea","sourcePath":"components/core/Textarea.jsx"},{"name":"TrustItem","sourcePath":"components/core/TrustItem.jsx"}],"startingPoints":[{"name":"BeforeAfter","path":"components/core/BeforeAfter.jsx","previewPath":"components/core/beforeafter.card.html","kind":"component","section":"Core","subtitle":"Draggable before/after comparison slider","viewport":"700x440"},{"name":"Button","path":"components/core/Button.jsx","previewPath":"components/core/beforeafter.card.html","kind":"component","section":"Core","subtitle":"Buttons — primary, secondary, ghost, inverse","viewport":"700x150"},{"name":"SectionHeading","path":"components/core/SectionHeading.jsx","previewPath":"components/core/beforeafter.card.html","kind":"component","section":"Core","subtitle":"Section header with eyebrow + serif title","viewport":"700x220"}],"cards":[{"path":"guidelines/logo.html","group":"Brand","viewport":"700x320","subtitle":"Wordmark, monogram, light & dark","name":"Logo"},{"path":"guidelines/motifs.html","group":"Brand","viewport":"700x200","subtitle":"Section marker + photo protection gradient","name":"Motifs — gold rule & image scrim"},{"path":"guidelines/colors-brand.html","group":"Colors","viewport":"700x180","subtitle":"Deep navy base + warm amber accent","name":"Brand — Navy & Amber"},{"path":"guidelines/colors-neutrals.html","group":"Colors","viewport":"700x180","subtitle":"Warm-tinted grays, not cold gray","name":"Neutrals — Warm stone"},{"path":"guidelines/colors-semantic.html","group":"Colors","viewport":"700x150","subtitle":"Status colors — used sparingly","name":"Semantic"},{"path":"components/core/beforeafter.card.html","group":"Components","viewport":"700x440","subtitle":"Draggable comparison — signature component","name":"Before / After slider"},{"path":"components/core/buttons.card.html","group":"Components","viewport":"700x260","subtitle":"Button variants, PhoneLink, Badge","name":"Buttons & actions"},{"path":"components/core/content.card.html","group":"Components","viewport":"700x340","subtitle":"SectionHeading, ServiceCard, TrustItem","name":"Content blocks"},{"path":"components/core/forms.card.html","group":"Components","viewport":"700x340","subtitle":"Input, Select, Textarea","name":"Form fields"},{"path":"guidelines/radius.html","group":"Spacing","viewport":"700x160","subtitle":"Restrained — 2 to 22px + pill","name":"Corner radii"},{"path":"guidelines/shadow.html","group":"Spacing","viewport":"700x180","subtitle":"Soft, navy-tinted shadows","name":"Elevation"},{"path":"guidelines/spacing-scale.html","group":"Spacing","viewport":"700x180","subtitle":"4px base · 1–10 steps","name":"Spacing scale"},{"path":"guidelines/type-body.html","group":"Type","viewport":"700x230","subtitle":"Readable grotesque body text","name":"Body & lead — Hanken Grotesk"},{"path":"guidelines/type-display.html","group":"Type","viewport":"700x200","subtitle":"Editorial high-contrast serif","name":"Display — Newsreader"},{"path":"guidelines/type-eyebrow.html","group":"Type","viewport":"700x150","subtitle":"Uppercase overline + italic accent","name":"Eyebrow & accent"},{"path":"guidelines/type-headings.html","group":"Type","viewport":"700x260","subtitle":"H1–H4 · Newsreader","name":"Headings scale"},{"path":"ui_kits/website/index.html","group":"Website","viewport":"1280x880","subtitle":"Sticky header, hero, services, why-us, before/after, areas, CTA, footer","name":"Marketing site — Home"}],"globalCssPaths":["tokens/fonts.css","tokens/colors.css","tokens/typography.css","tokens/spacing.css","tokens/base.css","styles.css"],"tokens":[{"name":"--navy-950","value":"#0a1626","kind":"color","definedIn":"tokens/colors.css"},{"name":"--navy-900","value":"#0f2034","kind":"color","definedIn":"tokens/colors.css"},{"name":"--navy-800","value":"#14263d","kind":"color","definedIn":"tokens/colors.css"},{"name":"--navy-700","value":"#1d3553","kind":"color","definedIn":"tokens/colors.css"},{"name":"--navy-600","value":"#2a4870","kind":"color","definedIn":"tokens/colors.css"},{"name":"--amber-700","value":"#9a6a26","kind":"color","definedIn":"tokens/colors.css"},{"name":"--amber-600","value":"#b07f30","kind":"color","definedIn":"tokens/colors.css"},{"name":"--amber-500","value":"#c18a3d","kind":"color","definedIn":"tokens/colors.css"},{"name":"--amber-400","value":"#d4a25c","kind":"color","definedIn":"tokens/colors.css"},{"name":"--amber-300","value":"#e4c08f","kind":"color","definedIn":"tokens/colors.css"},{"name":"--amber-100","value":"#f6ecd9","kind":"color","definedIn":"tokens/colors.css"},{"name":"--amber-50","value":"#faf4e9","kind":"color","definedIn":"tokens/colors.css"},{"name":"--white","value":"#ffffff","kind":"color","definedIn":"tokens/colors.css"},{"name":"--paper","value":"#faf8f4","kind":"color","definedIn":"tokens/colors.css"},{"name":"--cloud","value":"#f3efe8","kind":"color","definedIn":"tokens/colors.css"},{"name":"--stone-200","value":"#e6e0d6","kind":"color","definedIn":"tokens/colors.css"},{"name":"--stone-300","value":"#d2cabb","kind":"color","definedIn":"tokens/colors.css"},{"name":"--stone-400","value":"#a9a193","kind":"color","definedIn":"tokens/colors.css"},{"name":"--stone-500","value":"#7c7468","kind":"color","definedIn":"tokens/colors.css"},{"name":"--stone-600","value":"#574f44","kind":"color","definedIn":"tokens/colors.css"},{"name":"--ink","value":"#1b1814","kind":"color","definedIn":"tokens/colors.css"},{"name":"--success","value":"#2f7d52","kind":"color","definedIn":"tokens/colors.css"},{"name":"--warning","value":"#c98a1e","kind":"color","definedIn":"tokens/colors.css"},{"name":"--danger","value":"#b23b2e","kind":"color","definedIn":"tokens/colors.css"},{"name":"--info","value":"#2b6daf","kind":"color","definedIn":"tokens/colors.css"},{"name":"--surface-page","value":"var(--paper)","kind":"color","definedIn":"tokens/colors.css"},{"name":"--surface-card","value":"var(--white)","kind":"color","definedIn":"tokens/colors.css"},{"name":"--surface-panel","value":"var(--cloud)","kind":"color","definedIn":"tokens/colors.css"},{"name":"--surface-inverse","value":"var(--navy-900)","kind":"color","definedIn":"tokens/colors.css"},{"name":"--surface-inverse-2","value":"var(--navy-800)","kind":"color","definedIn":"tokens/colors.css"},{"name":"--surface-accent-soft","value":"var(--amber-50)","kind":"color","definedIn":"tokens/colors.css"},{"name":"--text-strong","value":"var(--ink)","kind":"font","definedIn":"tokens/colors.css"},{"name":"--text-body","value":"var(--stone-600)","kind":"font","definedIn":"tokens/colors.css"},{"name":"--text-muted","value":"var(--stone-500)","kind":"font","definedIn":"tokens/colors.css"},{"name":"--text-on-dark","value":"#f4f1ea","kind":"font","definedIn":"tokens/colors.css"},{"name":"--text-on-dark-muted","value":"#b9c2cf","kind":"font","definedIn":"tokens/colors.css"},{"name":"--text-accent","value":"var(--amber-600)","kind":"font","definedIn":"tokens/colors.css"},{"name":"--border-subtle","value":"var(--stone-200)","kind":"color","definedIn":"tokens/colors.css"},{"name":"--border-default","value":"var(--stone-300)","kind":"color","definedIn":"tokens/colors.css"},{"name":"--border-strong","value":"var(--stone-400)","kind":"color","definedIn":"tokens/colors.css"},{"name":"--border-on-dark","value":"rgba(255, 255, 255, 0.14)","kind":"color","definedIn":"tokens/colors.css"},{"name":"--brand-navy","value":"var(--navy-900)","kind":"color","definedIn":"tokens/colors.css"},{"name":"--brand-accent","value":"var(--amber-500)","kind":"color","definedIn":"tokens/colors.css"},{"name":"--brand-accent-hover","value":"var(--amber-600)","kind":"color","definedIn":"tokens/colors.css"},{"name":"--ring","value":"color-mix(in oklch, var(--amber-500) 65%, white)","kind":"color","definedIn":"tokens/colors.css"},{"name":"--font-serif","value":"\"Newsreader\", \"Iowan Old Style\", Georgia, \"Times New Roman\", serif","kind":"font","definedIn":"tokens/typography.css"},{"name":"--font-sans","value":"\"Hanken Grotesk\", ui-sans-serif, system-ui, -apple-system, \"Segoe UI\", sans-serif","kind":"font","definedIn":"tokens/typography.css"},{"name":"--font-display","value":"var(--font-serif)","kind":"font","definedIn":"tokens/typography.css"},{"name":"--font-heading","value":"var(--font-serif)","kind":"font","definedIn":"tokens/typography.css"},{"name":"--font-body","value":"var(--font-sans)","kind":"font","definedIn":"tokens/typography.css"},{"name":"--font-ui","value":"var(--font-sans)","kind":"font","definedIn":"tokens/typography.css"},{"name":"--fs-display-xl","value":"4.5rem","kind":"spacing","definedIn":"tokens/typography.css"},{"name":"--fs-display-l","value":"3.5rem","kind":"spacing","definedIn":"tokens/typography.css"},{"name":"--fs-display-m","value":"2.75rem","kind":"spacing","definedIn":"tokens/typography.css"},{"name":"--fs-h1","value":"2.25rem","kind":"spacing","definedIn":"tokens/typography.css"},{"name":"--fs-h2","value":"1.75rem","kind":"spacing","definedIn":"tokens/typography.css"},{"name":"--fs-h3","value":"1.375rem","kind":"spacing","definedIn":"tokens/typography.css"},{"name":"--fs-h4","value":"1.125rem","kind":"spacing","definedIn":"tokens/typography.css"},{"name":"--fs-body-lg","value":"1.1875rem","kind":"spacing","definedIn":"tokens/typography.css"},{"name":"--fs-body","value":"1rem","kind":"spacing","definedIn":"tokens/typography.css"},{"name":"--fs-small","value":"0.875rem","kind":"spacing","definedIn":"tokens/typography.css"},{"name":"--fs-eyebrow","value":"0.78rem","kind":"spacing","definedIn":"tokens/typography.css"},{"name":"--fw-light","value":"300","kind":"other","definedIn":"tokens/typography.css","annotation":"other"},{"name":"--fw-regular","value":"400","kind":"other","definedIn":"tokens/typography.css","annotation":"other"},{"name":"--fw-medium","value":"500","kind":"other","definedIn":"tokens/typography.css","annotation":"other"},{"name":"--fw-semibold","value":"600","kind":"other","definedIn":"tokens/typography.css","annotation":"other"},{"name":"--fw-bold","value":"700","kind":"other","definedIn":"tokens/typography.css","annotation":"other"},{"name":"--lh-tight","value":"1.08","kind":"other","definedIn":"tokens/typography.css","annotation":"other"},{"name":"--lh-snug","value":"1.2","kind":"other","definedIn":"tokens/typography.css","annotation":"other"},{"name":"--lh-normal","value":"1.5","kind":"other","definedIn":"tokens/typography.css","annotation":"other"},{"name":"--lh-relaxed","value":"1.65","kind":"other","definedIn":"tokens/typography.css","annotation":"other"},{"name":"--ls-tight","value":"-0.02em","kind":"other","definedIn":"tokens/typography.css","annotation":"other"},{"name":"--ls-normal","value":"0","kind":"other","definedIn":"tokens/typography.css","annotation":"other"},{"name":"--ls-wide","value":"0.04em","kind":"other","definedIn":"tokens/typography.css","annotation":"other"},{"name":"--ls-eyebrow","value":"0.18em","kind":"other","definedIn":"tokens/typography.css","annotation":"other"},{"name":"--space-0","value":"0","kind":"spacing","definedIn":"tokens/spacing.css"},{"name":"--space-1","value":"0.25rem","kind":"spacing","definedIn":"tokens/spacing.css"},{"name":"--space-2","value":"0.5rem","kind":"spacing","definedIn":"tokens/spacing.css"},{"name":"--space-3","value":"0.75rem","kind":"spacing","definedIn":"tokens/spacing.css"},{"name":"--space-4","value":"1rem","kind":"spacing","definedIn":"tokens/spacing.css"},{"name":"--space-5","value":"1.5rem","kind":"spacing","definedIn":"tokens/spacing.css"},{"name":"--space-6","value":"2rem","kind":"spacing","definedIn":"tokens/spacing.css"},{"name":"--space-7","value":"3rem","kind":"spacing","definedIn":"tokens/spacing.css"},{"name":"--space-8","value":"4rem","kind":"spacing","definedIn":"tokens/spacing.css"},{"name":"--space-9","value":"6rem","kind":"spacing","definedIn":"tokens/spacing.css"},{"name":"--space-10","value":"8rem","kind":"spacing","definedIn":"tokens/spacing.css"},{"name":"--radius-xs","value":"2px","kind":"radius","definedIn":"tokens/spacing.css"},{"name":"--radius-sm","value":"4px","kind":"radius","definedIn":"tokens/spacing.css"},{"name":"--radius-md","value":"8px","kind":"radius","definedIn":"tokens/spacing.css"},{"name":"--radius-lg","value":"14px","kind":"radius","definedIn":"tokens/spacing.css"},{"name":"--radius-xl","value":"22px","kind":"radius","definedIn":"tokens/spacing.css"},{"name":"--radius-pill","value":"999px","kind":"radius","definedIn":"tokens/spacing.css"},{"name":"--border-hairline","value":"1px","kind":"spacing","definedIn":"tokens/spacing.css"},{"name":"--border-thick","value":"2px","kind":"spacing","definedIn":"tokens/spacing.css"},{"name":"--shadow-xs","value":"0 1px 2px rgba(20, 24, 33, 0.06)","kind":"shadow","definedIn":"tokens/spacing.css"},{"name":"--shadow-sm","value":"0 2px 8px rgba(20, 24, 33, 0.07)","kind":"shadow","definedIn":"tokens/spacing.css"},{"name":"--shadow-md","value":"0 10px 28px -8px rgba(15, 32, 52, 0.16)","kind":"shadow","definedIn":"tokens/spacing.css"},{"name":"--shadow-lg","value":"0 24px 60px -18px rgba(15, 32, 52, 0.28)","kind":"shadow","definedIn":"tokens/spacing.css"},{"name":"--shadow-accent","value":"0 12px 30px -10px rgba(193, 138, 61, 0.5)","kind":"shadow","definedIn":"tokens/spacing.css"},{"name":"--container-max","value":"1200px","kind":"spacing","definedIn":"tokens/spacing.css"},{"name":"--container-narrow","value":"760px","kind":"spacing","definedIn":"tokens/spacing.css"},{"name":"--gutter","value":"clamp(1.25rem, 4vw, 3rem)","kind":"spacing","definedIn":"tokens/spacing.css","annotation":"spacing"},{"name":"--header-h","value":"84px","kind":"spacing","definedIn":"tokens/spacing.css"},{"name":"--ease-out","value":"cubic-bezier(0.22, 0.61, 0.36, 1)","kind":"other","definedIn":"tokens/spacing.css","annotation":"other"},{"name":"--ease-in-out","value":"cubic-bezier(0.65, 0, 0.35, 1)","kind":"other","definedIn":"tokens/spacing.css","annotation":"other"},{"name":"--dur-fast","value":"140ms","kind":"other","definedIn":"tokens/spacing.css","annotation":"other"},{"name":"--dur-base","value":"240ms","kind":"other","definedIn":"tokens/spacing.css","annotation":"other"},{"name":"--dur-slow","value":"420ms","kind":"other","definedIn":"tokens/spacing.css","annotation":"other"}],"themes":[],"fonts":[],"brandFonts":[{"family":"Newsreader","status":"ok","tokens":["--font-serif"],"path":"tokens/typography.css"},{"family":"Hanken Grotesk","status":"ok","tokens":["--font-sans"],"path":"tokens/typography.css"}],"source":"spa"}